keycloak/__init__.py
keycloak/_version.py
keycloak/authorization/__init__.py
keycloak/authorization/permission.py
keycloak/authorization/policy.py
keycloak/authorization/role.py
keycloak/connection.py
keycloak/exceptions.py
keycloak/keycloak_admin.py
keycloak/keycloak_openid.py
keycloak/keycloak_uma.py
keycloak/openid_connection.py
keycloak/pkce_utils.py
keycloak/py.typed
keycloak/uma_permissions.py
keycloak/urls_patterns.py
python_keycloak-7.0.2.dist-info/METADATA
python_keycloak-7.0.2.dist-info/WHEEL
python_keycloak-7.0.2.dist-info/licenses/LICENSE
python_keycloak-7.0.2.dist-info/RECORD
