Metadata-Version: 2.4
Name: python-keycloak
Version: 7.0.2
Summary: python-keycloak is a Python package providing access to the Keycloak API.
License: MIT
License-File: LICENSE
Keywords: keycloak,openid,oidc
Author: Marcos Pereira
Author-email: marcospereira.mpj@gmail.com
Requires-Python: >=3.10,<4
Classifier: Development Status :: 3 - Alpha
Classifier: License :: OSI Approved :: MIT License
Classifier: Operating System :: MacOS
Classifier: Operating System :: Microsoft :: Windows
Classifier: Operating System :: Unix
Classifier: Programming Language :: Python :: 3
Classifier: Programming Language :: Python :: 3.10
Classifier: Programming Language :: Python :: 3.11
Classifier: Programming Language :: Python :: 3.12
Classifier: Programming Language :: Python :: 3.13
Classifier: Programming Language :: Python :: 3.14
Classifier: Topic :: Utilities
Requires-Dist: aiofiles (>=24.1.0)
Requires-Dist: deprecation (>=2.1.0)
Requires-Dist: httpx (>=0.23.2)
Requires-Dist: jwcrypto (>=1.5.4)
Requires-Dist: requests (>=2.20.0)
Requires-Dist: requests-toolbelt (>=0.6.0)
Project-URL: Changelog, https://raw.githubusercontent.com/marcospereirampj/python-keycloak/master/CHANGELOG.md
Project-URL: Documentation, https://python-keycloak.readthedocs.io/en/latest/
Project-URL: Issue tracker, https://github.com/marcospereirampj/python-keycloak/issues
